pypi_pkg_test/__init__.py
pypi_pkg_test/main.py
pypi_pkg_test-0.0.4.dist-info/METADATA
pypi_pkg_test-0.0.4.dist-info/RECORD
pypi_pkg_test-0.0.4.dist-info/WHEEL
pypi_pkg_test-0.0.4.dist-info/top_level.txt
