Metadata-Version: 2.1
Name: pypi-pkg-test
Version: 0.0.4
Summary: A small test about distrubution
Home-page: https://github.com/jasonqiao36/pypi-pkg-test
Author: jasonqiao36
Author-email: jasonqiao36@gmail.com
License: UNKNOWN
Platform: UNKNOWN
Classifier: Programming Language :: Python :: 3
Classifier: License :: OSI Approved :: MIT License
Classifier: Operating System :: OS Independent
